yggdrasil_engine/__init__.py
yggdrasil_engine/custom_strategy.py
yggdrasil_engine/engine.py
yggdrasil_engine/lib/yggdrasilffi.dll
yggdrasil_engine-0.1.6.dist-info/METADATA
yggdrasil_engine-0.1.6.dist-info/WHEEL
yggdrasil_engine-0.1.6.dist-info/RECORD
