Metadata-Version: 2.1
Name: yggdrasil-engine
Version: 0.1.6
Summary: Engine for evaluating Unleash feature flags
License: MIT
Author: Simon Hornby
Author-email: liquidwicked64@gmail.com
Requires-Python: >=3.8,<4.0
Classifier: License :: OSI Approved :: MIT License
Classifier: Programming Language :: Python :: 3
Classifier: Programming Language :: Python :: 3.8
Classifier: Programming Language :: Python :: 3.9
Classifier: Programming Language :: Python :: 3.10
Classifier: Programming Language :: Python :: 3.11
Classifier: Programming Language :: Python :: 3.12
